pdfsentinel/__init__.py
pdfsentinel/sentinel.py
pdfsentinel/helper/pymupdf.py
pdfsentinel-1.1.0.dist-info/METADATA
pdfsentinel-1.1.0.dist-info/WHEEL
pdfsentinel-1.1.0.dist-info/licenses/LICENCE
pdfsentinel-1.1.0.dist-info/RECORD
