Metadata-Version: 2.4
Name: PDFSentinel
Version: 1.1.0
Summary: PDF Sentinel is a lightweight safety inspection library for PDF documents. It detects oversized, vector-heavy, or otherwise resource-intensive pages (like blueprints) that could slow down or crash OCR and pipelines.
Project-URL: Homepage, https://github.com/not-empty/pdf-sentinel-python
Project-URL: Issues, https://github.com/not-empty/pdf-sentinel-python/issues
Author-email: Not Empty Foundation <dev@not-empty.org>
License-File: LICENCE
Classifier: License :: OSI Approved :: GNU General Public License v3 (GPLv3)
Classifier: Operating System :: OS Independent
Classifier: Programming Language :: Python :: 3
Requires-Python: >=3.10
Requires-Dist: pymupdf>=1.26.6
